httpie_kws.py
httpie_kws-1.1.1.dist-info/METADATA
httpie_kws-1.1.1.dist-info/WHEEL
httpie_kws-1.1.1.dist-info/entry_points.txt
httpie_kws-1.1.1.dist-info/top_level.txt
httpie_kws-1.1.1.dist-info/RECORD
