Metadata-Version: 2.4
Name: httpie-kws
Version: 1.1.1
Summary: KWS plugin for HTTPie.
Author-email: Luo Jiejun <ljj@knd.com.cn>
License: Apache 2.0
Project-URL: Homepage, https://github.com/windtail/httpie-kws
Requires-Python: >=3.8
Requires-Dist: httpie>=3.2
